gitdoap.py
gitdoap-0.1.1.dist-info/METADATA
gitdoap-0.1.1.dist-info/WHEEL
gitdoap-0.1.1.dist-info/entry_points.txt
gitdoap-0.1.1.dist-info/RECORD
